my_engineer/__init__.py
my_engineer/__main__.py
my_engineer/main.py
my_engineer/codebase_concatenator/__init__.py
my_engineer/codebase_concatenator/concatenator.py
my_engineer/codebase_concatenator/config.py
my_engineer/codebase_concatenator/file_utils.py
my_engineer/codebase_concatenator/main.py
my_engineer/context_management/__init__.py
my_engineer/context_management/smart_context_builder.py
my_engineer/conversation_manager/__init__.py
my_engineer/conversation_manager/conversation_manager.py
my_engineer/file_operator/__init__.py
my_engineer/file_operator/file_operator.py
my_engineer/file_operator/main.py
my_engineer/file_operator/src/__init__.py
my_engineer/file_operator/src/file_service.py
my_engineer/instruction_processor/__init__.py
my_engineer/instruction_processor/instruction_processor.py
my_engineer/instruction_processor/main.py
my_engineer/llm_prompter/__init__.py
my_engineer/llm_prompter/llm_prompter.py
my_engineer/llm_prompter/main.py
my_engineer/llm_prompter/src/__init__.py
my_engineer/llm_prompter/src/chat_engine.py
my_engineer/llm_prompter/src/context_utils.py
my_engineer/llm_prompter/src/settings.py
my_engineer/llm_providers/__init__.py
my_engineer/llm_providers/providers/__init__.py
my_engineer/llm_providers/providers/base_provider.py
my_engineer/llm_providers/providers/claude_provider.py
my_engineer/llm_providers/providers/exceptions.py
my_engineer/llm_providers/providers/factory.py
my_engineer/llm_providers/providers/haiku_provider.py
my_engineer/llm_providers/providers/utils.py
my_engineer/patch_processor/__init__.py
my_engineer/patch_processor/main.py
my_engineer/patch_processor/patch_processor.py
my_engineer/patch_processor/src/__init__.py
my_engineer/patch_processor/src/patch_service.py
my_engineer/prompt_post_processor/__init__.py
my_engineer/prompt_post_processor/prompt_post_processor.py
my_engineer/shared_models/__init__.py
my_engineer/shared_models/chat_models.py
my_engineer/shared_models/llm_response/__init__.py
my_engineer-0.1.11.dist-info/LICENSE
my_engineer-0.1.11.dist-info/METADATA
my_engineer-0.1.11.dist-info/WHEEL
my_engineer-0.1.11.dist-info/entry_points.txt
my_engineer-0.1.11.dist-info/top_level.txt
my_engineer-0.1.11.dist-info/RECORD
